{
"17": {
"name": "石川県",
"bounds": [
[
136.2102,
36.1215
],
[
137.3052,
37.5739
]
],
"units": 221
},
"01": {
"name": "北海道",
"bounds": [
[
139.3313,
41.1413
],
[
146.0254,
45.5843
]
],
"units": 269
},
"02": {
"name": "青森県",
"bounds": [
[
140.0562,
40.2822
],
[
141.6538,
41.3746
]
],
"units": 172
},
"03": {
"name": "岩手県",
"bounds": [
[
140.8137,
38.6652
],
[
142.0635,
40.4503
]
],
"units": 241
},
"04": {
"name": "宮城県",
"bounds": [
[
140.4951,
37.8096
],
[
141.6341,
38.9739
]
],
"units": 204
},
"05": {
"name": "秋田県",
"bounds": [
[
139.811,
38.9385
],
[
140.8512,
40.4942
]
],
"units": 241
},
"06": {
"name": "山形県",
"bounds": [
[
139.5983,
37.8027
],
[
140.5488,
39.1348
]
],
"units": 231
},
"07": {
"name": "福島県",
"bounds": [
[
139.3717,
36.8581
],
[
141.1513,
37.9665
]
],
"units": 422
},
"08": {
"name": "茨城県",
"bounds": [
[
139.7191,
35.7816
],
[
140.7792,
36.8914
]
],
"units": 382
},
"09": {
"name": "栃木県",
"bounds": [
[
139.3348,
36.1962
],
[
140.293,
37.0542
]
],
"units": 176
},
"10": {
"name": "群馬県",
"bounds": [
[
138.587,
36.1002
],
[
139.6661,
36.7597
]
],
"units": 208
},
"11": {
"name": "埼玉県",
"bounds": [
[
138.9478,
35.7481
],
[
139.9232,
36.275
]
],
"units": 371
},
"12": {
"name": "千葉県",
"bounds": [
[
139.7441,
34.8864
],
[
140.8155,
36.0172
]
],
"units": 349
},
"13": {
"name": "東京都",
"bounds": [
[
139.0965,
32.7988
],
[
139.9545,
36.1217
]
],
"units": 205
},
"14": {
"name": "神奈川県",
"bounds": [
[
138.9549,
35.1197
],
[
139.7657,
35.6795
]
],
"units": 201
},
"15": {
"name": "新潟県",
"bounds": [
[
137.7719,
36.7853
],
[
139.7306,
38.4204
]
],
"units": 417
},
"16": {
"name": "富山県",
"bounds": [
[
136.7555,
36.4455
],
[
137.6443,
36.9854
]
],
"units": 271
},
"18": {
"name": "福井県",
"bounds": [
[
135.4885,
35.3479
],
[
136.689,
36.3178
]
],
"units": 179
},
"19": {
"name": "山梨県",
"bounds": [
[
138.234,
35.3228
],
[
139.1326,
35.9035
]
],
"units": 244
},
"20": {
"name": "長野県",
"bounds": [
[
137.5702,
35.2018
],
[
138.6399,
37.0341
]
],
"units": 395
},
"21": {
"name": "岐阜県",
"bounds": [
[
136.3839,
35.137
],
[
137.5679,
36.3409
]
],
"units": 344
},
"22": {
"name": "静岡県",
"bounds": [
[
137.4486,
34.584
],
[
139.184,
35.3712
]
],
"units": 341
},
"23": {
"name": "愛知県",
"bounds": [
[
136.6218,
34.596
],
[
137.7562,
35.4245
]
],
"units": 268
},
"24": {
"name": "三重県",
"bounds": [
[
135.9333,
33.7414
],
[
136.9754,
35.294
]
],
"units": 340
},
"25": {
"name": "滋賀県",
"bounds": [
[
135.8155,
34.8225
],
[
136.4202,
35.582
]
],
"units": 204
},
"26": {
"name": "京都府",
"bounds": [
[
134.8528,
34.6484
],
[
135.9902,
35.8114
]
],
"units": 271
},
"27": {
"name": "大阪府",
"bounds": [
[
135.2168,
34.287
],
[
135.7185,
34.9605
]
],
"units": 301
},
"28": {
"name": "兵庫県",
"bounds": [
[
134.2675,
34.1373
],
[
135.4924,
35.7352
]
],
"units": 426
},
"29": {
"name": "奈良県",
"bounds": [
[
135.6439,
34.1431
],
[
136.0922,
34.7693
]
],
"units": 155
},
"30": {
"name": "和歌山県",
"bounds": [
[
135.0226,
33.4278
],
[
136.005,
34.409
]
],
"units": 232
},
"31": {
"name": "鳥取県",
"bounds": [
[
133.1036,
35.1516
],
[
134.5226,
35.6058
]
],
"units": 192
},
"32": {
"name": "島根県",
"bounds": [
[
131.6276,
34.3321
],
[
133.4549,
36.3279
]
],
"units": 289
},
"33": {
"name": "岡山県",
"bounds": [
[
133.3192,
34.4036
],
[
134.3506,
35.2832
]
],
"units": 402
},
"34": {
"name": "広島県",
"bounds": [
[
132.0942,
34.1241
],
[
133.5286,
34.9858
]
],
"units": 433
},
"35": {
"name": "山口県",
"bounds": [
[
130.7678,
33.8169
],
[
132.3937,
34.5918
]
],
"units": 226
},
"36": {
"name": "徳島県",
"bounds": [
[
133.7112,
33.593
],
[
134.7601,
34.2374
]
],
"units": 140
},
"37": {
"name": "香川県",
"bounds": [
[
133.5715,
34.032
],
[
134.4182,
34.5525
]
],
"units": 178
},
"38": {
"name": "愛媛県",
"bounds": [
[
132.2546,
32.9551
],
[
133.7095,
34.341
]
],
"units": 296
},
"39": {
"name": "高知県",
"bounds": [
[
132.5806,
32.7107
],
[
134.2997,
33.8797
]
],
"units": 197
},
"40": {
"name": "福岡県",
"bounds": [
[
130.0962,
33.0224
],
[
131.2108,
33.9669
]
],
"units": 343
},
"41": {
"name": "佐賀県",
"bounds": [
[
129.7587,
32.9982
],
[
130.5671,
33.5465
]
],
"units": 135
},
"42": {
"name": "長崎県",
"bounds": [
[
128.6406,
32.4131
],
[
130.5084,
34.6009
]
],
"units": 201
},
"43": {
"name": "熊本県",
"bounds": [
[
129.9378,
32.1221
],
[
131.2423,
33.151
]
],
"units": 364
},
"44": {
"name": "大分県",
"bounds": [
[
130.8076,
32.7784
],
[
132.0489,
33.7151
]
],
"units": 258
},
"45": {
"name": "宮崎県",
"bounds": [
[
130.8423,
31.3271
],
[
131.7573,
32.8992
]
],
"units": 100
},
"46": {
"name": "鹿児島県",
"bounds": [
[
128.6964,
27.2523
],
[
131.2576,
32.6104
]
],
"units": 145
},
"47": {
"name": "沖縄県",
"bounds": [
[
122.8495,
24.1905
],
[
132.0974,
27.0077
]
],
"units": 59
}
}